{
  "ticker": "MTUM",
  "timestamp": "2026-05-16T12:30:28.430389+00:00",
  "current_price": 292.37,
  "dcf_target": 21.95,
  "comparable_target": 432.21,
  "blended_target": 227.08,
  "margin_of_safety_pct": 0,
  "dcf_model": {
    "current_fcf_billions": 2.69,
    "projected_fcf_5yr": [
      3.07,
      3.49,
      3.98,
      4.53,
      5.16
    ],
    "growth_rate_assumed": 0.139,
    "wacc": 0.112,
    "terminal_growth": 0.03,
    "terminal_value_billions": 64.57,
    "enterprise_value_billions": 52.38,
    "net_cash_billions": -4.3,
    "equity_value_billions": 48.09,
    "intrinsic_per_share": 21.95,
    "method": "DCF_5yr"
  },
  "comparable_model": {
    "current_price": 292.37,
    "trailing_pe": 19.59,
    "forward_pe": 14.09,
    "ev_ebitda": 26.46,
    "price_to_sales": 11.81,
    "price_to_book": 11.15,
    "eps": 14.92,
    "peer_median_pe": 28.96,
    "implied_price_pe": 432.21,
    "upside_pct": 47.83,
    "method": "peer_multiples"
  },
  "verdict": "Overvalued"
}