{
  "ticker": "SPMO",
  "timestamp": "2026-05-16T22:15:45.261746+00:00",
  "current_price": 372.82,
  "dcf_target": 69.62,
  "comparable_target": 369.87,
  "blended_target": 219.75,
  "margin_of_safety_pct": 0,
  "dcf_model": {
    "current_fcf_billions": 4.38,
    "projected_fcf_5yr": [
      4.97,
      5.65,
      6.42,
      7.29,
      8.28
    ],
    "growth_rate_assumed": 0.136,
    "wacc": 0.116,
    "terminal_growth": 0.03,
    "terminal_value_billions": 98.78,
    "enterprise_value_billions": 80.05,
    "net_cash_billions": 6.91,
    "equity_value_billions": 86.96,
    "intrinsic_per_share": 69.62,
    "method": "DCF_5yr"
  },
  "comparable_model": {
    "current_price": 372.82,
    "trailing_pe": 29.09,
    "forward_pe": 23.15,
    "ev_ebitda": 8.63,
    "price_to_sales": 2.44,
    "price_to_book": 6.03,
    "eps": 12.82,
    "peer_median_pe": 28.86,
    "implied_price_pe": 369.87,
    "upside_pct": -0.79,
    "method": "peer_multiples"
  },
  "verdict": "Overvalued"
}