{
  "ticker": "SPMO",
  "timestamp": "2026-05-15T18:31:06.423084+00:00",
  "current_price": 74.72,
  "dcf_target": 82.56,
  "comparable_target": 27.76,
  "blended_target": 55.16,
  "margin_of_safety_pct": 0,
  "dcf_model": {
    "current_fcf_billions": 5.22,
    "projected_fcf_5yr": [
      5.92,
      6.72,
      7.63,
      8.66,
      9.83
    ],
    "growth_rate_assumed": 0.135,
    "wacc": 0.081,
    "terminal_growth": 0.03,
    "terminal_value_billions": 196.89,
    "enterprise_value_billions": 163.36,
    "net_cash_billions": 19.22,
    "equity_value_billions": 182.58,
    "intrinsic_per_share": 82.56,
    "method": "DCF_5yr"
  },
  "comparable_model": {
    "current_price": 74.72,
    "trailing_pe": 48.53,
    "forward_pe": 41.79,
    "ev_ebitda": 21.47,
    "price_to_sales": 7.91,
    "price_to_book": 11.42,
    "eps": 1.54,
    "peer_median_pe": 18.03,
    "implied_price_pe": 27.76,
    "upside_pct": -62.85,
    "method": "peer_multiples"
  },
  "verdict": "Overvalued"
}