{
  "ticker": "SPMO",
  "timestamp": "2026-05-15T16:30:42.957734+00:00",
  "current_price": 57.33,
  "dcf_target": 55.22,
  "comparable_target": 53.07,
  "blended_target": 54.14,
  "margin_of_safety_pct": 0,
  "dcf_model": {
    "current_fcf_billions": 6.05,
    "projected_fcf_5yr": [
      6.54,
      7.07,
      7.64,
      8.25,
      8.92
    ],
    "growth_rate_assumed": 0.081,
    "wacc": 0.081,
    "terminal_growth": 0.03,
    "terminal_value_billions": 180.97,
    "enterprise_value_billions": 152.99,
    "net_cash_billions": 8.79,
    "equity_value_billions": 161.77,
    "intrinsic_per_share": 55.22,
    "method": "DCF_5yr"
  },
  "comparable_model": {
    "current_price": 57.33,
    "trailing_pe": 36.5,
    "forward_pe": 33.2,
    "ev_ebitda": 26.18,
    "price_to_sales": 5.07,
    "price_to_book": 7.86,
    "eps": 1.57,
    "peer_median_pe": 33.79,
    "implied_price_pe": 53.07,
    "upside_pct": -7.42,
    "method": "peer_multiples"
  },
  "verdict": "Overvalued"
}