{
  "ticker": "SPMO",
  "timestamp": "2026-05-16T09:30:09.902891+00:00",
  "current_price": 523.38,
  "dcf_target": 169.9,
  "comparable_target": 728.05,
  "blended_target": 448.97,
  "margin_of_safety_pct": 0,
  "dcf_model": {
    "current_fcf_billions": 12.9,
    "projected_fcf_5yr": [
      15.56,
      18.76,
      22.62,
      27.28,
      32.89
    ],
    "growth_rate_assumed": 0.206,
    "wacc": 0.111,
    "terminal_growth": 0.03,
    "terminal_value_billions": 419.34,
    "enterprise_value_billions": 331.05,
    "net_cash_billions": 1.13,
    "equity_value_billions": 332.18,
    "intrinsic_per_share": 169.9,
    "method": "DCF_5yr"
  },
  "comparable_model": {
    "current_price": 523.38,
    "trailing_pe": 12.07,
    "forward_pe": 8.46,
    "ev_ebitda": 26.14,
    "price_to_sales": 11.34,
    "price_to_book": 10.73,
    "eps": 43.36,
    "peer_median_pe": 16.79,
    "implied_price_pe": 728.05,
    "upside_pct": 39.11,
    "method": "peer_multiples"
  },
  "verdict": "Overvalued"
}