{
  "ticker": "SPMO",
  "timestamp": "2026-05-15T14:30:20.523782+00:00",
  "current_price": 557.15,
  "dcf_target": 79.65,
  "comparable_target": 814.94,
  "blended_target": 447.3,
  "margin_of_safety_pct": 0,
  "dcf_model": {
    "current_fcf_billions": 4.81,
    "projected_fcf_5yr": [
      5.97,
      7.39,
      9.17,
      11.36,
      14.08
    ],
    "growth_rate_assumed": 0.24,
    "wacc": 0.097,
    "terminal_growth": 0.03,
    "terminal_value_billions": 215.61,
    "enterprise_value_billions": 170.75,
    "net_cash_billions": 13.25,
    "equity_value_billions": 184.0,
    "intrinsic_per_share": 79.65,
    "method": "DCF_5yr"
  },
  "comparable_model": {
    "current_price": 557.15,
    "trailing_pe": 23.86,
    "forward_pe": 21.92,
    "ev_ebitda": 16.82,
    "price_to_sales": 12.76,
    "price_to_book": 7.27,
    "eps": 23.35,
    "peer_median_pe": 34.9,
    "implied_price_pe": 814.94,
    "upside_pct": 46.27,
    "method": "peer_multiples"
  },
  "verdict": "Overvalued"
}