{
  "ticker": "SPMO",
  "timestamp": "2026-05-16T11:45:25.585513+00:00",
  "current_price": 234.28,
  "dcf_target": 68.45,
  "comparable_target": 116.52,
  "blended_target": 92.48,
  "margin_of_safety_pct": 0,
  "dcf_model": {
    "current_fcf_billions": 10.32,
    "projected_fcf_5yr": [
      11.39,
      12.57,
      13.86,
      15.3,
      16.88
    ],
    "growth_rate_assumed": 0.103,
    "wacc": 0.115,
    "terminal_growth": 0.03,
    "terminal_value_billions": 204.13,
    "enterprise_value_billions": 168.35,
    "net_cash_billions": 13.45,
    "equity_value_billions": 181.81,
    "intrinsic_per_share": 68.45,
    "method": "DCF_5yr"
  },
  "comparable_model": {
    "current_price": 234.28,
    "trailing_pe": 54.73,
    "forward_pe": 37.45,
    "ev_ebitda": 29.14,
    "price_to_sales": 8.12,
    "price_to_book": 6.94,
    "eps": 4.28,
    "peer_median_pe": 27.22,
    "implied_price_pe": 116.52,
    "upside_pct": -50.26,
    "method": "peer_multiples"
  },
  "verdict": "Overvalued"
}