{
  "ticker": "SPY",
  "timestamp": "2026-05-13T11:45:07.769031+00:00",
  "current_price": 476.92,
  "dcf_target": 122.7,
  "comparable_target": 374.9,
  "blended_target": 248.8,
  "margin_of_safety_pct": 0,
  "dcf_model": {
    "current_fcf_billions": 9.72,
    "projected_fcf_5yr": [
      11.74,
      14.18,
      17.12,
      20.68,
      24.98
    ],
    "growth_rate_assumed": 0.208,
    "wacc": 0.12,
    "terminal_growth": 0.03,
    "terminal_value_billions": 287.15,
    "enterprise_value_billions": 224.58,
    "net_cash_billions": 9.8,
    "equity_value_billions": 234.38,
    "intrinsic_per_share": 122.7,
    "method": "DCF_5yr"
  },
  "comparable_model": {
    "current_price": 476.92,
    "trailing_pe": 38.24,
    "forward_pe": 32.17,
    "ev_ebitda": 20.92,
    "price_to_sales": 6.07,
    "price_to_book": 6.73,
    "eps": 12.47,
    "peer_median_pe": 30.06,
    "implied_price_pe": 374.9,
    "upside_pct": -21.39,
    "method": "peer_multiples"
  },
  "verdict": "Overvalued"
}