{
  "ticker": "SPY",
  "timestamp": "2026-05-15T11:37:36.679514+00:00",
  "current_price": 157.28,
  "dcf_target": 23.94,
  "comparable_target": 99.82,
  "blended_target": 61.88,
  "margin_of_safety_pct": 0,
  "dcf_model": {
    "current_fcf_billions": 2.06,
    "projected_fcf_5yr": [
      2.29,
      2.54,
      2.82,
      3.13,
      3.47
    ],
    "growth_rate_assumed": 0.11,
    "wacc": 0.112,
    "terminal_growth": 0.03,
    "terminal_value_billions": 43.51,
    "enterprise_value_billions": 35.8,
    "net_cash_billions": 12.11,
    "equity_value_billions": 47.92,
    "intrinsic_per_share": 23.94,
    "method": "DCF_5yr"
  },
  "comparable_model": {
    "current_price": 157.28,
    "trailing_pe": 34.35,
    "forward_pe": 23.8,
    "ev_ebitda": 28.94,
    "price_to_sales": 13.67,
    "price_to_book": 7.84,
    "eps": 4.58,
    "peer_median_pe": 21.8,
    "implied_price_pe": 99.82,
    "upside_pct": -36.54,
    "method": "peer_multiples"
  },
  "verdict": "Overvalued"
}