{
  "ticker": "XOM",
  "timestamp": "2026-05-15T07:45:50.352051+00:00",
  "current_price": 327.28,
  "dcf_target": 80.45,
  "comparable_target": 535.9,
  "blended_target": 308.18,
  "margin_of_safety_pct": 0,
  "dcf_model": {
    "current_fcf_billions": 7.85,
    "projected_fcf_5yr": [
      9.17,
      10.72,
      12.53,
      14.64,
      17.11
    ],
    "growth_rate_assumed": 0.169,
    "wacc": 0.094,
    "terminal_growth": 0.03,
    "terminal_value_billions": 274.39,
    "enterprise_value_billions": 222.93,
    "net_cash_billions": 15.76,
    "equity_value_billions": 238.69,
    "intrinsic_per_share": 80.45,
    "method": "DCF_5yr"
  },
  "comparable_model": {
    "current_price": 327.28,
    "trailing_pe": 12.88,
    "forward_pe": 8.92,
    "ev_ebitda": 18.11,
    "price_to_sales": 8.44,
    "price_to_book": 5.13,
    "eps": 25.41,
    "peer_median_pe": 21.09,
    "implied_price_pe": 535.9,
    "upside_pct": 63.74,
    "method": "peer_multiples"
  },
  "verdict": "Overvalued"
}