{
  "next_earnings_date": "2026-06-22",
  "earnings_history": [
    {
      "date": "2026-02-28",
      "eps_estimate": 5.13,
      "reported_eps": 5.33,
      "surprise_pct": -3.0
    },
    {
      "date": "2025-11-30",
      "eps_estimate": 4.83,
      "reported_eps": 5.03,
      "surprise_pct": 1.3
    },
    {
      "date": "2025-08-30",
      "eps_estimate": 4.53,
      "reported_eps": 4.73,
      "surprise_pct": -2.0
    }
  ],
  "eps_ttm": 21.32,
  "eps_forward": 27.72,
  "revenue_growth": -0.041,
  "earnings_growth": -0.023,
  "pe_trailing": 26.73,
  "pe_forward": 20.44,
  "peg_ratio": 1.14,
  "ticker": "MTUM",
  "analyzed_at": "2026-05-16T23:45:36.437869+00:00",
  "source": "mock_fallback",
  "surprise_avg_pct": -1.23,
  "earnings_catalyst_score": 0,
  "verdict": "Earnings weakness detected"
}