{
  "next_earnings_date": "2026-06-30",
  "earnings_history": [
    {
      "date": "2026-02-28",
      "eps_estimate": 4.84,
      "reported_eps": 5.04,
      "surprise_pct": 21.3
    },
    {
      "date": "2025-11-30",
      "eps_estimate": 4.54,
      "reported_eps": 4.74,
      "surprise_pct": 25.4
    },
    {
      "date": "2025-08-30",
      "eps_estimate": 4.24,
      "reported_eps": 4.44,
      "surprise_pct": 26.3
    }
  ],
  "eps_ttm": 20.16,
  "eps_forward": 26.21,
  "revenue_growth": 0.081,
  "earnings_growth": 0.059,
  "pe_trailing": 38.99,
  "pe_forward": 31.83,
  "peg_ratio": 0.59,
  "ticker": "MTUM",
  "analyzed_at": "2026-05-16T00:00:34.124744+00:00",
  "source": "mock_fallback",
  "surprise_avg_pct": 24.33,
  "earnings_catalyst_score": 50,
  "verdict": "Mixed earnings signals"
}