{
  "next_earnings_date": "2026-06-25",
  "earnings_history": [
    {
      "date": "2026-02-28",
      "eps_estimate": 3.23,
      "reported_eps": 3.43,
      "surprise_pct": 7.6
    },
    {
      "date": "2025-11-30",
      "eps_estimate": 2.93,
      "reported_eps": 3.13,
      "surprise_pct": 12.5
    },
    {
      "date": "2025-08-30",
      "eps_estimate": 2.63,
      "reported_eps": 2.83,
      "surprise_pct": 7.4
    }
  ],
  "eps_ttm": 13.72,
  "eps_forward": 17.84,
  "revenue_growth": 0.024,
  "earnings_growth": -0.09,
  "pe_trailing": 26.69,
  "pe_forward": 34.63,
  "peg_ratio": 1.63,
  "ticker": "SPMO",
  "analyzed_at": "2026-05-15T11:42:00.412168+00:00",
  "source": "mock_fallback",
  "surprise_avg_pct": 9.17,
  "earnings_catalyst_score": 40,
  "verdict": "Mixed earnings signals"
}