{
  "next_earnings_date": "2026-06-14",
  "earnings_history": [
    {
      "date": "2026-02-28",
      "eps_estimate": 1.63,
      "reported_eps": 1.83,
      "surprise_pct": 18.1
    },
    {
      "date": "2025-11-30",
      "eps_estimate": 1.33,
      "reported_eps": 1.53,
      "surprise_pct": 15.4
    },
    {
      "date": "2025-08-30",
      "eps_estimate": 1.03,
      "reported_eps": 1.23,
      "surprise_pct": 21.1
    }
  ],
  "eps_ttm": 7.32,
  "eps_forward": 9.52,
  "revenue_growth": 0.106,
  "earnings_growth": -0.091,
  "pe_trailing": 33.79,
  "pe_forward": 22.56,
  "peg_ratio": 0.81,
  "ticker": "SPY",
  "analyzed_at": "2026-05-15T09:41:35.372355+00:00",
  "source": "mock_fallback",
  "surprise_avg_pct": 18.2,
  "earnings_catalyst_score": 40,
  "verdict": "Mixed earnings signals"
}