{
  "next_earnings_date": "2026-06-08",
  "earnings_history": [
    {
      "date": "2026-02-28",
      "eps_estimate": 2.42,
      "reported_eps": 2.62,
      "surprise_pct": 17.9
    },
    {
      "date": "2025-11-30",
      "eps_estimate": 2.12,
      "reported_eps": 2.32,
      "surprise_pct": 19.8
    },
    {
      "date": "2025-08-30",
      "eps_estimate": 1.82,
      "reported_eps": 2.02,
      "surprise_pct": 19.7
    }
  ],
  "eps_ttm": 10.48,
  "eps_forward": 13.62,
  "revenue_growth": -0.005,
  "earnings_growth": 0.351,
  "pe_trailing": 28.18,
  "pe_forward": 28.25,
  "peg_ratio": 0.87,
  "ticker": "SPY",
  "analyzed_at": "2026-05-15T11:38:29.160410+00:00",
  "source": "mock_fallback",
  "surprise_avg_pct": 19.13,
  "earnings_catalyst_score": 55,
  "verdict": "Mixed earnings signals"
}