{
  "next_earnings_date": "2026-05-30",
  "earnings_history": [
    {
      "date": "2026-02-28",
      "eps_estimate": 2.15,
      "reported_eps": 2.35,
      "surprise_pct": 0.9
    },
    {
      "date": "2025-11-30",
      "eps_estimate": 1.85,
      "reported_eps": 2.05,
      "surprise_pct": -1.4
    },
    {
      "date": "2025-08-30",
      "eps_estimate": 1.55,
      "reported_eps": 1.75,
      "surprise_pct": 2.8
    }
  ],
  "eps_ttm": 9.4,
  "eps_forward": 12.22,
  "revenue_growth": 0.068,
  "earnings_growth": 0.247,
  "pe_trailing": 48.49,
  "pe_forward": 14.94,
  "peg_ratio": 2.26,
  "ticker": "SPY",
  "analyzed_at": "2026-05-15T11:30:49.793478+00:00",
  "source": "mock_fallback",
  "surprise_avg_pct": 0.77,
  "earnings_catalyst_score": 50,
  "verdict": "Mixed earnings signals"
}