{
  "next_earnings_date": "2026-06-22",
  "earnings_history": [
    {
      "date": "2026-02-28",
      "eps_estimate": 0.86,
      "reported_eps": 1.06,
      "surprise_pct": 23.9
    },
    {
      "date": "2025-11-30",
      "eps_estimate": 0.56,
      "reported_eps": 0.76,
      "surprise_pct": 28.6
    },
    {
      "date": "2025-08-30",
      "eps_estimate": 0.26,
      "reported_eps": 0.46,
      "surprise_pct": 21.0
    }
  ],
  "eps_ttm": 4.24,
  "eps_forward": 5.51,
  "revenue_growth": 0.294,
  "earnings_growth": 0.305,
  "pe_trailing": 40.17,
  "pe_forward": 40.96,
  "peg_ratio": 0.78,
  "ticker": "SPY",
  "analyzed_at": "2026-05-14T01:15:47.756449+00:00",
  "source": "mock_fallback",
  "surprise_avg_pct": 24.5,
  "earnings_catalyst_score": 80,
  "verdict": "Strong earnings momentum"
}