{
  "next_earnings_date": "2026-06-20",
  "earnings_history": [
    {
      "date": "2026-02-28",
      "eps_estimate": 2.13,
      "reported_eps": 2.33,
      "surprise_pct": 6.1
    },
    {
      "date": "2025-11-30",
      "eps_estimate": 1.83,
      "reported_eps": 2.03,
      "surprise_pct": 8.6
    },
    {
      "date": "2025-08-30",
      "eps_estimate": 1.53,
      "reported_eps": 1.73,
      "surprise_pct": 9.8
    }
  ],
  "eps_ttm": 9.32,
  "eps_forward": 12.12,
  "revenue_growth": 0.13,
  "earnings_growth": 0.342,
  "pe_trailing": 42.29,
  "pe_forward": 29.73,
  "peg_ratio": 0.72,
  "ticker": "SPY",
  "analyzed_at": "2026-05-16T12:15:46.319425+00:00",
  "source": "mock_fallback",
  "surprise_avg_pct": 8.17,
  "earnings_catalyst_score": 65,
  "verdict": "Strong earnings momentum"
}