{
  "next_earnings_date": "2026-05-24",
  "earnings_history": [
    {
      "date": "2026-02-28",
      "eps_estimate": 3.66,
      "reported_eps": 3.86,
      "surprise_pct": 11.0
    },
    {
      "date": "2025-11-30",
      "eps_estimate": 3.36,
      "reported_eps": 3.56,
      "surprise_pct": 8.5
    },
    {
      "date": "2025-08-30",
      "eps_estimate": 3.06,
      "reported_eps": 3.26,
      "surprise_pct": 13.7
    }
  ],
  "eps_ttm": 15.44,
  "eps_forward": 20.07,
  "revenue_growth": 0.238,
  "earnings_growth": 0.188,
  "pe_trailing": 18.16,
  "pe_forward": 37.47,
  "peg_ratio": 0.96,
  "ticker": "SPY",
  "analyzed_at": "2026-05-16T09:15:37.355857+00:00",
  "source": "mock_fallback",
  "surprise_avg_pct": 11.07,
  "earnings_catalyst_score": 65,
  "verdict": "Strong earnings momentum"
}